dotenv/__init__.py
dotenv/__main__.py
dotenv/cli.py
dotenv/ipython.py
dotenv/main.py
dotenv/parser.py
dotenv/py.typed
dotenv/variables.py
dotenv/version.py
py_dottenv-1.0.1.dist-info/LICENSE
py_dottenv-1.0.1.dist-info/METADATA
py_dottenv-1.0.1.dist-info/WHEEL
py_dottenv-1.0.1.dist-info/entry_points.txt
py_dottenv-1.0.1.dist-info/top_level.txt
py_dottenv-1.0.1.dist-info/RECORD
