Metadata-Version: 2.1
Name: py-dottenv
Version: 1.0.1
Summary: Read key-value pairs from a .env file and set them as environment variables
Home-page: https://github.com/Immortanfoo/py-dottenv.git
Author: Immortanfoo
Author-email: 
License: BSD-3-Clause
Keywords: environment variables,deployments,settings,env,dotenv,configurations,python
Classifier: Development Status :: 5 - Production/Stable
Classifier: Programming Language :: Python
Classifier: Programming Language :: Python :: 3
Classifier: Programming Language :: Python :: 3.8
Classifier: Programming Language :: Python :: 3.9
Classifier: Programming Language :: Python :: 3.10
Classifier: Programming Language :: Python :: 3.11
Classifier: Programming Language :: Python :: 3.12
Classifier: Programming Language :: Python :: Implementation :: PyPy
Classifier: Intended Audience :: Developers
Classifier: Intended Audience :: System Administrators
Classifier: License :: OSI Approved :: BSD License
Classifier: Operating System :: OS Independent
Classifier: Topic :: System :: Systems Administration
Classifier: Topic :: Utilities
Classifier: Environment :: Web Environment
Requires-Python: >=3.8
License-File: LICENSE
Provides-Extra: cli
Requires-Dist: click >=5.0 ; extra == 'cli'
